{
  "species": "cobblemon:moltres",
  "order": 1,
  "variations": [
    {
      "aspects": [
        "mythical_blazing"
      ],
      "texture": "cobblemon:textures/pokemon/0146_moltres/moltres_blazing.png",
      "layers": [
        {
          "name": "emissive",
          "emissive": true,
          "texture": "cobblemon:textures/pokemon/0146_moltres/moltres_emissive_blazing.png",
          "translucent": true
        }
      ]
    },
    {
      "aspects": [
        "mythical_blazing",
        "shiny"
      ],
      "texture": "cobblemon:textures/pokemon/0146_moltres/moltres_shiny_blazing.png",
      "layers": [
        {
          "name": "emissive",
          "emissive": true,
          "texture": "cobblemon:textures/pokemon/0146_moltres/moltres_shiny_emissive_blazing.png",
          "translucent": true
        }
      ]
    },
    {
      "aspects": [
        "mythical_radiant"
      ],
      "texture": "cobblemon:textures/pokemon/0146_moltres/moltres_radiant.png",
      "layers": [
        {
          "name": "emissive",
          "emissive": true,
          "texture": "cobblemon:textures/pokemon/0146_moltres/moltres_emissive_radiant.png",
          "translucent": true
        }
      ]
    },
    {
      "aspects": [
        "mythical_radiant",
        "mythical_blazing",
        "shiny"
      ],
      "texture": "cobblemon:textures/pokemon/0146_moltres/moltres_shiny_radiant.png",
      "layers": [
        {
          "name": "emissive",
          "emissive": true,
          "texture": "cobblemon:textures/pokemon/0146_moltres/moltres_shiny_emissive_radiant.png",
          "translucent": true
        }
      ]
    },
    {
      "aspects": [
        "mythical_radiant",
        "mythical_blazing"
      ],
      "texture": "cobblemon:textures/pokemon/0146_moltres/moltres_blazing_radiant.png",
      "layers": [
        {
          "name": "emissive",
          "emissive": true,
          "texture": "cobblemon:textures/pokemon/0146_moltres/moltres_emissive_blazing_radiant.png",
          "translucent": true
        }
      ]
    },
    {
      "aspects": [
        "mythical_radiant",
        "shiny"
      ],
      "texture": "cobblemon:textures/pokemon/0146_moltres/moltres_shiny_blazing_radiant.png",
      "layers": [
        {
          "name": "emissive",
          "emissive": true,
          "texture": "cobblemon:textures/pokemon/0146_moltres/moltres_shiny_emissive_blazing_radiant.png",
          "translucent": true
        }
      ]
    },
    {
      "aspects": [
        "mythical_rainbow"
      ],
      "texture": "cobblemon:textures/pokemon/0146_moltres/moltres_rainbow.png",
      "layers": [
        {
          "name": "emissive",
          "emissive": true,
          "texture": "cobblemon:textures/pokemon/0146_moltres/moltres_emissive_rainbow.png",
          "translucent": true
        }
      ]
    },
    {
      "aspects": [
        "mythical_rainbow",
        "shiny"
      ],
      "texture": "cobblemon:textures/pokemon/0146_moltres/moltres_shiny_rainbow.png",
      "layers": [
        {
          "name": "emissive",
          "emissive": true,
          "texture": "cobblemon:textures/pokemon/0146_moltres/moltres_emissive_rainbow.png",
          "translucent": true
        }
      ]
    },
    {
      "aspects": [
        "mythical_radiant",
        "mythical_rainbow"
      ],
      "texture": "cobblemon:textures/pokemon/0146_moltres/moltres_rainbow_radiant.png",
      "layers": [
        {
          "name": "emissive",
          "emissive": true,
          "texture": "cobblemon:textures/pokemon/0146_moltres/moltres_emissive_rainbow_radiant.png",
          "translucent": true
        }
      ]
    },
    {
      "aspects": [
        "mythical_radiant",
        "mythical_rainbow",
        "shiny"
      ],
      "texture": "cobblemon:textures/pokemon/0146_moltres/moltres_shiny_rainbow_radiant.png",
      "layers": [
        {
          "name": "emissive",
          "emissive": true,
          "texture": "cobblemon:textures/pokemon/0146_moltres/moltres_emissive_rainbow_radiant.png",
          "translucent": true
        }
      ]
    },
    {
      "aspects": [
        "mythical_matrix"
      ],
      "texture": "cobblemon:textures/pokemon/0146_moltres/moltres_matrix.png",
      "layers": [
        {
          "name": "emissive",
          "emissive": true,
          "texture": "cobblemon:textures/pokemon/0146_moltres/moltres_emissive_matrix.png",
          "translucent": true
        }
      ]
    },
    {
      "aspects": [
        "mythical_matrix",
        "mythical_blazing",
        "shiny"
      ],
      "texture": "cobblemon:textures/pokemon/0146_moltres/moltres_shiny_matrix.png",
      "layers": [
        {
          "name": "emissive",
          "emissive": true,
          "texture": "cobblemon:textures/pokemon/0146_moltres/moltres_shiny_emissive_matrix.png",
          "translucent": true
        }
      ]
    },
    {
      "aspects": [
        "mythical_matrix",
        "mythical_blazing"
      ],
      "texture": "cobblemon:textures/pokemon/0146_moltres/moltres_blazing_matrix.png",
      "layers": [
        {
          "name": "emissive",
          "emissive": true,
          "texture": "cobblemon:textures/pokemon/0146_moltres/moltres_emissive_blazing_matrix.png",
          "translucent": true
        }
      ]
    },
    {
      "aspects": [
        "mythical_matrix",
        "shiny"
      ],
      "texture": "cobblemon:textures/pokemon/0146_moltres/moltres_shiny_blazing_matrix.png",
      "layers": [
        {
          "name": "emissive",
          "emissive": true,
          "texture": "cobblemon:textures/pokemon/0146_moltres/moltres_shiny_emissive_blazing_matrix.png",
          "translucent": true
        }
      ]
    },
    {
      "aspects": [
        "mythical_matrix",
        "mythical_rainbow"
      ],
      "texture": "cobblemon:textures/pokemon/0146_moltres/moltres_rainbow_matrix.png",
      "layers": [
        {
          "name": "emissive",
          "emissive": true,
          "texture": "cobblemon:textures/pokemon/0146_moltres/moltres_emissive_rainbow_matrix.png",
          "translucent": true
        }
      ]
    },
    {
      "aspects": [
        "mythical_matrix",
        "mythical_rainbow",
        "shiny"
      ],
      "texture": "cobblemon:textures/pokemon/0146_moltres/moltres_shiny_rainbow_matrix.png",
      "layers": [
        {
          "name": "emissive",
          "emissive": true,
          "texture": "cobblemon:textures/pokemon/0146_moltres/moltres_emissive_rainbow_matrix.png",
          "translucent": true
        }
      ]
    },
    {
      "aspects": [
        "mythical_galaxy"
      ],
      "texture": "cobblemon:textures/pokemon/0146_moltres/moltres_galaxy.png",
      "layers": [
        {
          "name": "emissive",
          "emissive": true,
          "texture": "cobblemon:textures/pokemon/0146_moltres/moltres_emissive_galaxy.png",
          "translucent": true
        }
      ]
    },
    {
      "aspects": [
        "mythical_galaxy",
        "mythical_blazing",
        "shiny"
      ],
      "texture": "cobblemon:textures/pokemon/0146_moltres/moltres_shiny_galaxy.png",
      "layers": [
        {
          "name": "emissive",
          "emissive": true,
          "texture": "cobblemon:textures/pokemon/0146_moltres/moltres_shiny_emissive_galaxy.png",
          "translucent": true
        }
      ]
    },
    {
      "aspects": [
        "mythical_galaxy",
        "mythical_blazing"
      ],
      "texture": "cobblemon:textures/pokemon/0146_moltres/moltres_blazing_galaxy.png",
      "layers": [
        {
          "name": "emissive",
          "emissive": true,
          "texture": "cobblemon:textures/pokemon/0146_moltres/moltres_emissive_blazing_galaxy.png",
          "translucent": true
        }
      ]
    },
    {
      "aspects": [
        "mythical_galaxy",
        "shiny"
      ],
      "texture": "cobblemon:textures/pokemon/0146_moltres/moltres_shiny_blazing_galaxy.png",
      "layers": [
        {
          "name": "emissive",
          "emissive": true,
          "texture": "cobblemon:textures/pokemon/0146_moltres/moltres_shiny_emissive_blazing_galaxy.png",
          "translucent": true
        }
      ]
    },
    {
      "aspects": [
        "mythical_galaxy",
        "mythical_rainbow"
      ],
      "texture": "cobblemon:textures/pokemon/0146_moltres/moltres_rainbow_galaxy.png",
      "layers": [
        {
          "name": "emissive",
          "emissive": true,
          "texture": "cobblemon:textures/pokemon/0146_moltres/moltres_emissive_rainbow_galaxy.png",
          "translucent": true
        }
      ]
    },
    {
      "aspects": [
        "mythical_galaxy",
        "mythical_rainbow",
        "shiny"
      ],
      "texture": "cobblemon:textures/pokemon/0146_moltres/moltres_shiny_rainbow_galaxy.png",
      "layers": [
        {
          "name": "emissive",
          "emissive": true,
          "texture": "cobblemon:textures/pokemon/0146_moltres/moltres_emissive_rainbow_galaxy.png",
          "translucent": true
        }
      ]
    },
    {
      "aspects": [
        "mythical_glitch"
      ],
      "texture": "cobblemon:textures/pokemon/0146_moltres/moltres_glitch.png",
      "layers": [
        {
          "name": "emissive",
          "emissive": true,
          "texture": "cobblemon:textures/pokemon/0146_moltres/moltres_emissive_glitch.png",
          "translucent": true
        }
      ]
    },
    {
      "aspects": [
        "mythical_glitch",
        "mythical_blazing",
        "shiny"
      ],
      "texture": "cobblemon:textures/pokemon/0146_moltres/moltres_shiny_glitch.png",
      "layers": [
        {
          "name": "emissive",
          "emissive": true,
          "texture": "cobblemon:textures/pokemon/0146_moltres/moltres_shiny_emissive_glitch.png",
          "translucent": true
        }
      ]
    },
    {
      "aspects": [
        "mythical_glitch",
        "mythical_blazing"
      ],
      "texture": "cobblemon:textures/pokemon/0146_moltres/moltres_blazing_glitch.png",
      "layers": [
        {
          "name": "emissive",
          "emissive": true,
          "texture": "cobblemon:textures/pokemon/0146_moltres/moltres_emissive_blazing_glitch.png",
          "translucent": true
        }
      ]
    },
    {
      "aspects": [
        "mythical_glitch",
        "shiny"
      ],
      "texture": "cobblemon:textures/pokemon/0146_moltres/moltres_shiny_blazing_glitch.png",
      "layers": [
        {
          "name": "emissive",
          "emissive": true,
          "texture": "cobblemon:textures/pokemon/0146_moltres/moltres_shiny_emissive_blazing_glitch.png",
          "translucent": true
        }
      ]
    },
    {
      "aspects": [
        "mythical_glitch",
        "mythical_rainbow"
      ],
      "texture": "cobblemon:textures/pokemon/0146_moltres/moltres_rainbow_glitch.png",
      "layers": [
        {
          "name": "emissive",
          "emissive": true,
          "texture": "cobblemon:textures/pokemon/0146_moltres/moltres_emissive_rainbow_glitch.png",
          "translucent": true
        }
      ]
    },
    {
      "aspects": [
        "mythical_glitch",
        "mythical_rainbow",
        "shiny"
      ],
      "texture": "cobblemon:textures/pokemon/0146_moltres/moltres_shiny_rainbow_glitch.png",
      "layers": [
        {
          "name": "emissive",
          "emissive": true,
          "texture": "cobblemon:textures/pokemon/0146_moltres/moltres_emissive_rainbow_glitch.png",
          "translucent": true
        }
      ]
    },
    {
      "aspects": [
        "mythical_magma"
      ],
      "texture": "cobblemon:textures/pokemon/0146_moltres/moltres_magma.png",
      "layers": [
        {
          "name": "emissive",
          "emissive": true,
          "texture": "cobblemon:textures/pokemon/0146_moltres/moltres_emissive_magma.png",
          "translucent": true
        }
      ]
    },
    {
      "aspects": [
        "mythical_magma",
        "mythical_blazing",
        "shiny"
      ],
      "texture": "cobblemon:textures/pokemon/0146_moltres/moltres_shiny_magma.png",
      "layers": [
        {
          "name": "emissive",
          "emissive": true,
          "texture": "cobblemon:textures/pokemon/0146_moltres/moltres_shiny_emissive_magma.png",
          "translucent": true
        }
      ]
    },
    {
      "aspects": [
        "mythical_magma",
        "mythical_blazing"
      ],
      "texture": "cobblemon:textures/pokemon/0146_moltres/moltres_blazing_magma.png",
      "layers": [
        {
          "name": "emissive",
          "emissive": true,
          "texture": "cobblemon:textures/pokemon/0146_moltres/moltres_emissive_blazing_magma.png",
          "translucent": true
        }
      ]
    },
    {
      "aspects": [
        "mythical_magma",
        "shiny"
      ],
      "texture": "cobblemon:textures/pokemon/0146_moltres/moltres_shiny_blazing_magma.png",
      "layers": [
        {
          "name": "emissive",
          "emissive": true,
          "texture": "cobblemon:textures/pokemon/0146_moltres/moltres_shiny_emissive_blazing_magma.png",
          "translucent": true
        }
      ]
    },
    {
      "aspects": [
        "mythical_magma",
        "mythical_rainbow"
      ],
      "texture": "cobblemon:textures/pokemon/0146_moltres/moltres_rainbow_magma.png",
      "layers": [
        {
          "name": "emissive",
          "emissive": true,
          "texture": "cobblemon:textures/pokemon/0146_moltres/moltres_emissive_rainbow_magma.png",
          "translucent": true
        }
      ]
    },
    {
      "aspects": [
        "mythical_magma",
        "mythical_rainbow",
        "shiny"
      ],
      "texture": "cobblemon:textures/pokemon/0146_moltres/moltres_shiny_rainbow_magma.png",
      "layers": [
        {
          "name": "emissive",
          "emissive": true,
          "texture": "cobblemon:textures/pokemon/0146_moltres/moltres_emissive_rainbow_magma.png",
          "translucent": true
        }
      ]
    },
    {
      "aspects": [
        "mythical_fireworks"
      ],
      "texture": "cobblemon:textures/pokemon/0146_moltres/moltres_fireworks.png",
      "layers": [
        {
          "name": "emissive",
          "emissive": true,
          "texture": "cobblemon:textures/pokemon/0146_moltres/moltres_emissive_fireworks.png",
          "translucent": true
        }
      ]
    },
    {
      "aspects": [
        "mythical_fireworks",
        "mythical_blazing",
        "shiny"
      ],
      "texture": "cobblemon:textures/pokemon/0146_moltres/moltres_shiny_fireworks.png",
      "layers": [
        {
          "name": "emissive",
          "emissive": true,
          "texture": "cobblemon:textures/pokemon/0146_moltres/moltres_shiny_emissive_fireworks.png",
          "translucent": true
        }
      ]
    },
    {
      "aspects": [
        "mythical_fireworks",
        "mythical_blazing"
      ],
      "texture": "cobblemon:textures/pokemon/0146_moltres/moltres_blazing_fireworks.png",
      "layers": [
        {
          "name": "emissive",
          "emissive": true,
          "texture": "cobblemon:textures/pokemon/0146_moltres/moltres_emissive_blazing_fireworks.png",
          "translucent": true
        }
      ]
    },
    {
      "aspects": [
        "mythical_fireworks",
        "shiny"
      ],
      "texture": "cobblemon:textures/pokemon/0146_moltres/moltres_shiny_blazing_fireworks.png",
      "layers": [
        {
          "name": "emissive",
          "emissive": true,
          "texture": "cobblemon:textures/pokemon/0146_moltres/moltres_shiny_emissive_blazing_fireworks.png",
          "translucent": true
        }
      ]
    },
    {
      "aspects": [
        "mythical_fireworks",
        "mythical_rainbow"
      ],
      "texture": "cobblemon:textures/pokemon/0146_moltres/moltres_rainbow_fireworks.png",
      "layers": [
        {
          "name": "emissive",
          "emissive": true,
          "texture": "cobblemon:textures/pokemon/0146_moltres/moltres_emissive_rainbow_fireworks.png",
          "translucent": true
        }
      ]
    },
    {
      "aspects": [
        "mythical_fireworks",
        "mythical_rainbow",
        "shiny"
      ],
      "texture": "cobblemon:textures/pokemon/0146_moltres/moltres_shiny_rainbow_fireworks.png",
      "layers": [
        {
          "name": "emissive",
          "emissive": true,
          "texture": "cobblemon:textures/pokemon/0146_moltres/moltres_emissive_rainbow_fireworks.png",
          "translucent": true
        }
      ]
    },
    {
      "aspects": [
        "radar_spawned"
      ],
      "texture": "cobblemon:textures/pokemon/0146_moltres/moltres_holographic.png",
      "layers": [
        {
          "name": "emissive",
          "emissive": true,
          "texture": "cobblemon:textures/pokemon/0146_moltres/moltres_emissive_holographic.png",
          "translucent": true
        }
      ]
    },
    {
      "aspects": [
        "radar_spawned",
        "mythical_blazing",
        "shiny"
      ],
      "texture": "cobblemon:textures/pokemon/0146_moltres/moltres_shiny_holographic.png",
      "layers": [
        {
          "name": "emissive",
          "emissive": true,
          "texture": "cobblemon:textures/pokemon/0146_moltres/moltres_shiny_emissive_holographic.png",
          "translucent": true
        }
      ]
    },
    {
      "aspects": [
        "radar_spawned",
        "mythical_blazing"
      ],
      "texture": "cobblemon:textures/pokemon/0146_moltres/moltres_blazing_holographic.png",
      "layers": [
        {
          "name": "emissive",
          "emissive": true,
          "texture": "cobblemon:textures/pokemon/0146_moltres/moltres_emissive_blazing_holographic.png",
          "translucent": true
        }
      ]
    },
    {
      "aspects": [
        "radar_spawned",
        "shiny"
      ],
      "texture": "cobblemon:textures/pokemon/0146_moltres/moltres_shiny_blazing_holographic.png",
      "layers": [
        {
          "name": "emissive",
          "emissive": true,
          "texture": "cobblemon:textures/pokemon/0146_moltres/moltres_shiny_emissive_blazing_holographic.png",
          "translucent": true
        }
      ]
    },
    {
      "aspects": [
        "radar_spawned",
        "mythical_rainbow"
      ],
      "texture": "cobblemon:textures/pokemon/0146_moltres/moltres_rainbow_holographic.png",
      "layers": [
        {
          "name": "emissive",
          "emissive": true,
          "texture": "cobblemon:textures/pokemon/0146_moltres/moltres_emissive_rainbow_holographic.png",
          "translucent": true
        }
      ]
    },
    {
      "aspects": [
        "radar_spawned",
        "mythical_rainbow",
        "shiny"
      ],
      "texture": "cobblemon:textures/pokemon/0146_moltres/moltres_shiny_rainbow_holographic.png",
      "layers": [
        {
          "name": "emissive",
          "emissive": true,
          "texture": "cobblemon:textures/pokemon/0146_moltres/moltres_emissive_rainbow_holographic.png",
          "translucent": true
        }
      ]
    }
  ]
}