{
  "species": "cobblemon:mew",
  "order": 1,
  "variations": [
    {
      "aspects": [
        "mythical_blazing"
      ],
      "texture": "cobblemon:textures/pokemon/0151_mew/mew_blazing.png"
    },
    {
      "aspects": [
        "mythical_blazing",
        "shiny"
      ],
      "texture": "cobblemon:textures/pokemon/0151_mew/mew_shiny_blazing.png"
    },
    {
      "aspects": [
        "mythical_radiant"
      ],
      "texture": "cobblemon:textures/pokemon/0151_mew/mew_radiant.png"
    },
    {
      "aspects": [
        "mythical_radiant",
        "shiny"
      ],
      "texture": "cobblemon:textures/pokemon/0151_mew/mew_shiny_radiant.png"
    },
    {
      "aspects": [
        "mythical_radiant",
        "mythical_blazing"
      ],
      "texture": "cobblemon:textures/pokemon/0151_mew/mew_blazing_radiant.png"
    },
    {
      "aspects": [
        "mythical_radiant",
        "mythical_blazing",
        "shiny"
      ],
      "texture": "cobblemon:textures/pokemon/0151_mew/mew_shiny_blazing_radiant.png"
    },
    {
      "aspects": [
        "mythical_rainbow"
      ],
      "texture": "cobblemon:textures/pokemon/0151_mew/mew_rainbow.png"
    },
    {
      "aspects": [
        "mythical_rainbow",
        "shiny"
      ],
      "texture": "cobblemon:textures/pokemon/0151_mew/mew_shiny_rainbow.png"
    },
    {
      "aspects": [
        "mythical_radiant",
        "mythical_rainbow"
      ],
      "texture": "cobblemon:textures/pokemon/0151_mew/mew_rainbow_radiant.png"
    },
    {
      "aspects": [
        "mythical_radiant",
        "mythical_rainbow",
        "shiny"
      ],
      "texture": "cobblemon:textures/pokemon/0151_mew/mew_shiny_rainbow_radiant.png"
    },
    {
      "aspects": [
        "mythical_matrix"
      ],
      "texture": "cobblemon:textures/pokemon/0151_mew/mew_matrix.png"
    },
    {
      "aspects": [
        "mythical_matrix",
        "shiny"
      ],
      "texture": "cobblemon:textures/pokemon/0151_mew/mew_shiny_matrix.png"
    },
    {
      "aspects": [
        "mythical_matrix",
        "mythical_blazing"
      ],
      "texture": "cobblemon:textures/pokemon/0151_mew/mew_blazing_matrix.png"
    },
    {
      "aspects": [
        "mythical_matrix",
        "mythical_blazing",
        "shiny"
      ],
      "texture": "cobblemon:textures/pokemon/0151_mew/mew_shiny_blazing_matrix.png"
    },
    {
      "aspects": [
        "mythical_matrix",
        "mythical_rainbow"
      ],
      "texture": "cobblemon:textures/pokemon/0151_mew/mew_rainbow_matrix.png"
    },
    {
      "aspects": [
        "mythical_matrix",
        "mythical_rainbow",
        "shiny"
      ],
      "texture": "cobblemon:textures/pokemon/0151_mew/mew_shiny_rainbow_matrix.png"
    },
    {
      "aspects": [
        "mythical_galaxy"
      ],
      "texture": "cobblemon:textures/pokemon/0151_mew/mew_galaxy.png"
    },
    {
      "aspects": [
        "mythical_galaxy",
        "shiny"
      ],
      "texture": "cobblemon:textures/pokemon/0151_mew/mew_shiny_galaxy.png"
    },
    {
      "aspects": [
        "mythical_galaxy",
        "mythical_blazing"
      ],
      "texture": "cobblemon:textures/pokemon/0151_mew/mew_blazing_galaxy.png"
    },
    {
      "aspects": [
        "mythical_galaxy",
        "mythical_blazing",
        "shiny"
      ],
      "texture": "cobblemon:textures/pokemon/0151_mew/mew_shiny_blazing_galaxy.png"
    },
    {
      "aspects": [
        "mythical_galaxy",
        "mythical_rainbow"
      ],
      "texture": "cobblemon:textures/pokemon/0151_mew/mew_rainbow_galaxy.png"
    },
    {
      "aspects": [
        "mythical_galaxy",
        "mythical_rainbow",
        "shiny"
      ],
      "texture": "cobblemon:textures/pokemon/0151_mew/mew_shiny_rainbow_galaxy.png"
    },
    {
      "aspects": [
        "mythical_glitch"
      ],
      "texture": "cobblemon:textures/pokemon/0151_mew/mew_glitch.png"
    },
    {
      "aspects": [
        "mythical_glitch",
        "shiny"
      ],
      "texture": "cobblemon:textures/pokemon/0151_mew/mew_shiny_glitch.png"
    },
    {
      "aspects": [
        "mythical_glitch",
        "mythical_blazing"
      ],
      "texture": "cobblemon:textures/pokemon/0151_mew/mew_blazing_glitch.png"
    },
    {
      "aspects": [
        "mythical_glitch",
        "mythical_blazing",
        "shiny"
      ],
      "texture": "cobblemon:textures/pokemon/0151_mew/mew_shiny_blazing_glitch.png"
    },
    {
      "aspects": [
        "mythical_glitch",
        "mythical_rainbow"
      ],
      "texture": "cobblemon:textures/pokemon/0151_mew/mew_rainbow_glitch.png"
    },
    {
      "aspects": [
        "mythical_glitch",
        "mythical_rainbow",
        "shiny"
      ],
      "texture": "cobblemon:textures/pokemon/0151_mew/mew_shiny_rainbow_glitch.png"
    },
    {
      "aspects": [
        "mythical_magma"
      ],
      "texture": "cobblemon:textures/pokemon/0151_mew/mew_magma.png"
    },
    {
      "aspects": [
        "mythical_magma",
        "shiny"
      ],
      "texture": "cobblemon:textures/pokemon/0151_mew/mew_shiny_magma.png"
    },
    {
      "aspects": [
        "mythical_magma",
        "mythical_blazing"
      ],
      "texture": "cobblemon:textures/pokemon/0151_mew/mew_blazing_magma.png"
    },
    {
      "aspects": [
        "mythical_magma",
        "mythical_blazing",
        "shiny"
      ],
      "texture": "cobblemon:textures/pokemon/0151_mew/mew_shiny_blazing_magma.png"
    },
    {
      "aspects": [
        "mythical_magma",
        "mythical_rainbow"
      ],
      "texture": "cobblemon:textures/pokemon/0151_mew/mew_rainbow_magma.png"
    },
    {
      "aspects": [
        "mythical_magma",
        "mythical_rainbow",
        "shiny"
      ],
      "texture": "cobblemon:textures/pokemon/0151_mew/mew_shiny_rainbow_magma.png"
    },
    {
      "aspects": [
        "mythical_fireworks"
      ],
      "texture": "cobblemon:textures/pokemon/0151_mew/mew_fireworks.png"
    },
    {
      "aspects": [
        "mythical_fireworks",
        "shiny"
      ],
      "texture": "cobblemon:textures/pokemon/0151_mew/mew_shiny_fireworks.png"
    },
    {
      "aspects": [
        "mythical_fireworks",
        "mythical_blazing"
      ],
      "texture": "cobblemon:textures/pokemon/0151_mew/mew_blazing_fireworks.png"
    },
    {
      "aspects": [
        "mythical_fireworks",
        "mythical_blazing",
        "shiny"
      ],
      "texture": "cobblemon:textures/pokemon/0151_mew/mew_shiny_blazing_fireworks.png"
    },
    {
      "aspects": [
        "mythical_fireworks",
        "mythical_rainbow"
      ],
      "texture": "cobblemon:textures/pokemon/0151_mew/mew_rainbow_fireworks.png"
    },
    {
      "aspects": [
        "mythical_fireworks",
        "mythical_rainbow",
        "shiny"
      ],
      "texture": "cobblemon:textures/pokemon/0151_mew/mew_shiny_rainbow_fireworks.png"
    }
  ]
}